README.md
hello_tea.py
setup.py
tea_xyz1.egg-info/PKG-INFO
tea_xyz1.egg-info/SOURCES.txt
tea_xyz1.egg-info/dependency_links.txt
tea_xyz1.egg-info/entry_points.txt
tea_xyz1.egg-info/requires.txt
tea_xyz1.egg-info/top_level.txt