Metadata-Version: 2.1
Name: tea-xyz1
Version: 1.0.3
Summary: A simple package for https://app.tea.xyz/
Home-page: https://github.com/madest92/tea-xyz1
Author: Alex
Author-email: madest92@mail.com
License: UNKNOWN
Project-URL: Homepage, https://github.com/madest92/tea-xyz1
Project-URL: Source, https://github.com/madest92/tea-xyz1
Platform: UNKNOWN
Classifier: License :: OSI Approved :: MIT License
Classifier: Programming Language :: Python :: 3
Classifier: Programming Language :: Python :: 3.6
Classifier: Programming Language :: Python :: 3.7
Classifier: Programming Language :: Python :: 3.8
Classifier: Programming Language :: Python :: 3.9
Requires-Python: >=3.6
